{
  "book": [
    {
      "title": "Τα μαθηματικά μου δημιουργικές δραστηριότητες για τους μαθητές της Ε΄ δημοτικού",
      "subtitle": null,
      "image": "http://www.biblionet.gr/images/covers/b2157.jpg",
      "author": [
        {
          "name": "Γιώργος Σ. Δρούλιας",
          "b_id": "3364"
        }
      ],
      "contributors": {
        "εικονογράφηση": [
          {
            "name": "Ναταλία Καπατσούλια",
            "b_id": "3365"
          }
        ],
        "επιμέλεια σειράς": [
          {
            "name": "Ισίδωρος Γ. Χριστόπουλος",
            "b_id": "3366"
          }
        ]
      },
      "publisher": {
        "text": "Μίνωας",
        "b_id": "75"
      },
      "isbn": "960-240-877-4",
      "isbn_13": "978-960-240-877-3",
      "award": [

      ],
      "description": null,
      "category": [
        {
          "ddc": "372.7",
          "name": "Μαθηματικά - Σπουδή και διδασκαλία",
          "b_id": "454"
        }
      ],
      "b_id": "2157",
      "publication": {
        "year": "1998",
        "version": "1",
        "place": "Αθήνα"
      },
      "format": "Βιβλίο",
      "original_language": null,
      "original_title": null,
      "price": "12,23",
      "availability": "Εξαντλημένο",
      "last_update": "30/4/2013",
      "series": {
      },
      "physical_description": {
        "pages": "184",
        "size": "24x17",
        "cover_type": "Μαλακό εξώφυλλο"
      }
    }
  ]
}